LICENSE
README.md
setup.py
ih_common.egg-info/PKG-INFO
ih_common.egg-info/SOURCES.txt
ih_common.egg-info/dependency_links.txt
ih_common.egg-info/top_level.txt
inhand/__init__.py
inhand/cloud/Information.py
inhand/cloud/__init__.py
inhand/dto/ErrorException.py
inhand/dto/Message.py
inhand/dto/Model.py
inhand/dto/RestAPIResult.py
inhand/dto/RestfulApi.py
inhand/dto/__init__.py
inhand/service/CacheService.py
inhand/service/CalendarService.py
inhand/service/ConsulService.py
inhand/service/HdfsService.py
inhand/service/LBSService.py
inhand/service/MQSender.py
inhand/service/MongoService.py
inhand/service/RDBService.py
inhand/service/SettingService.py
inhand/service/StorageService.py
inhand/service/ZkService.py
inhand/service/__init__.py
inhand/utilities/DateTimeUtility.py
inhand/utilities/GNSSTools.py
inhand/utilities/HttpUtil.py
inhand/utilities/JSONUtil.py
inhand/utilities/StringUtil.py
inhand/utilities/URLUtility.py
inhand/utilities/Utility.py
inhand/utilities/__init__.py