Metadata-Version: 2.1
Name: ih-common
Version: 2.18.2
Summary: tool
Home-page: https://gitlab.inhand.design/hancj-dev/py-common
Author: hanchuanjun
Author-email: han@inhand.com.cn
License: MIT
Classifier: Programming Language :: Python :: 3
Classifier: License :: OSI Approved :: MIT License
Classifier: Operating System :: OS Independent
Requires-Python: >=3.7
License-File: LICENSE
